LICENSE
MANIFEST.in
README.rst
setup.py
test_bakthat.py
bakthat/__init__.py
bakthat/backends.py
bakthat/conf.py
bakthat/helper.py
bakthat/models.py
bakthat/plugin.py
bakthat/sync.py
bakthat/sync_wip.py
bakthat/utils.py
bakthat.egg-info/PKG-INFO
bakthat.egg-info/SOURCES.txt
bakthat.egg-info/dependency_links.txt
bakthat.egg-info/entry_points.txt
bakthat.egg-info/not-zip-safe
bakthat.egg-info/requires.txt
bakthat.egg-info/top_level.txt
test/test_plugin.py
test/test_plugin2.py