Metadata-Version: 1.1
Name: bakthat
Version: 0.6.0
Summary: Bakthat is a MIT licensed backup framework written in Python, it's both a command line tool and a Python module that helps you manage backups on Amazon S3/Glacier and OpenStack Swift. It automatically compress, encrypt (symmetric encryption) and upload your files.
Home-page: http://docs.bakthat.io
Author: Thomas Sileo
Author-email: thomas.sileo@gmail.com
License: MIT
Keywords: aws s3 glacier backup restore archive
Platform: UNKNOWN
Classifier: Development Status :: 4 - Beta
Classifier: Intended Audience :: Developers
Classifier: Topic :: System :: Archiving :: Backup
Classifier: License :: OSI Approved :: MIT License
Classifier: Programming Language :: Python
